merakifirewalledservices/merakiFirewalledServices.py
merakifirewalledservices-0.1.3.dist-info/entry_points.txt
merakifirewalledservices-0.1.3.dist-info/LICENSE
merakifirewalledservices-0.1.3.dist-info/WHEEL
merakifirewalledservices-0.1.3.dist-info/METADATA
merakifirewalledservices-0.1.3.dist-info/RECORD
